setup.py
django_snowshoestamp.egg-info/PKG-INFO
django_snowshoestamp.egg-info/SOURCES.txt
django_snowshoestamp.egg-info/dependency_links.txt
django_snowshoestamp.egg-info/not-zip-safe
django_snowshoestamp.egg-info/requires.txt
django_snowshoestamp.egg-info/top_level.txt
snowshoestamp/__init__.py
snowshoestamp/admin.py
snowshoestamp/models.py
snowshoestamp/services.py
snowshoestamp/signals.py
snowshoestamp/urls.py
snowshoestamp/views.py