Metadata-Version: 1.0
Name: django-snowshoestamp
Version: 0.1.0
Summary: A Django app for integrating with snowshoestamp
Home-page: https://github.com/rosscdh/django-snowshoestamp
Author: Ross Crawford-d'Heureuse
Author-email: ross@lawpal.com
License: MIT
Platform: UNKNOWN
